imjoy_jupyter_extension/__init__.py
imjoy_jupyter_extension/static/imjoy-icon.png
imjoy_jupyter_extension/static/imjoy_jupyter_extension.yaml
imjoy_jupyter_extension/static/index.js
imjoy_jupyter_extension-0.3.0.data/data/etc/jupyter/nbconfig/notebook.d/imjoy_jupyter_extension.json
imjoy_jupyter_extension-0.3.0.data/data/share/jupyter/nbextensions/imjoy_jupyter_extension/imjoy-icon.png
imjoy_jupyter_extension-0.3.0.data/data/share/jupyter/nbextensions/imjoy_jupyter_extension/imjoy_jupyter_extension.yaml
imjoy_jupyter_extension-0.3.0.data/data/share/jupyter/nbextensions/imjoy_jupyter_extension/index.js
imjoy_jupyter_extension-0.3.0.dist-info/LICENSE
imjoy_jupyter_extension-0.3.0.dist-info/METADATA
imjoy_jupyter_extension-0.3.0.dist-info/WHEEL
imjoy_jupyter_extension-0.3.0.dist-info/top_level.txt
imjoy_jupyter_extension-0.3.0.dist-info/RECORD
