Metadata-Version: 2.1
Name: imjoy-jupyter-extension
Version: 0.3.0
Summary: Running ImJoy in Jupyter notebooks.
Home-page: http://github.com/imjoy-team/imjoy-jupyter-extension
Author: ImJoy Team
Author-email: imjoy.team@gmail.com
License: MIT
Platform: UNKNOWN
License-File: LICENSE
Requires-Dist: imjoy-rpc (>=0.3.35)
Requires-Dist: notebook (>=5.3)
